cryptology/__init__.py
cryptology/cryptology.py
cryptology/tools.py
cryptology-0.0.13.dist-info/LICENSE.txt
cryptology-0.0.13.dist-info/METADATA
cryptology-0.0.13.dist-info/WHEEL
cryptology-0.0.13.dist-info/top_level.txt
cryptology-0.0.13.dist-info/RECORD
