Metadata-Version: 2.1
Name: cryptology
Version: 0.0.13
Summary: Decrypt/Encrypt text using various cipher techniques
Home-page: UNKNOWN
Author: Antonio Felton
License: UNKNOWN
Platform: UNKNOWN
License-File: LICENSE.txt
